jj_d42/__init__.py
jj_d42/_version.py
jj_d42/py.typed
jj_d42/history_request/__init__.py
jj_d42/history_request/_history_request_generator.py
jj_d42/history_request/_history_request_schema.py
jj_d42/history_request/_history_request_substitutor.py
jj_d42/history_request/_history_request_validator.py
jj_d42/history_response/__init__.py
jj_d42/history_response/_history_response_generator.py
jj_d42/history_response/_history_response_schema.py
jj_d42/history_response/_history_response_substitutor.py
jj_d42/history_response/_history_response_validator.py
jj_d42/types/__init__.py
jj_d42/types/header_list/__init__.py
jj_d42/types/istr/__init__.py
jj_d42/types/param_list/__init__.py
jj_d42/types/unordered/__init__.py
jj_d42/types/unordered/_unordered_generator.py
jj_d42/types/unordered/_unordered_representor.py
jj_d42/types/unordered/_unordered_schema.py
jj_d42/types/unordered/_unordered_substitutor.py
jj_d42/types/unordered/_unordered_validator.py
jj_d42/utils/__init__.py
jj_d42-2.0.1.dist-info/LICENSE
jj_d42-2.0.1.dist-info/METADATA
jj_d42-2.0.1.dist-info/WHEEL
jj_d42-2.0.1.dist-info/top_level.txt
jj_d42-2.0.1.dist-info/RECORD
