Metadata-Version: 2.1
Name: jj-d42
Version: 2.0.1
Home-page: https://github.com/jj-mock/jj-d42
Author: Nikita Tsvetkov
Author-email: tsv1@fastmail.com
License: Apache-2.0
Project-URL: Docs, https://jj-mock.io/docs/integrations/d42
Project-URL: GitHub, https://github.com/jj-mock/jj-d42
Classifier: License :: OSI Approved :: Apache Software License
Classifier: Programming Language :: Python :: 3.8
Classifier: Programming Language :: Python :: 3.9
Classifier: Programming Language :: Python :: 3.10
Classifier: Programming Language :: Python :: 3.11
Classifier: Programming Language :: Python :: 3.12
Classifier: Typing :: Typed
Requires-Python: >=3.8
License-File: LICENSE
Requires-Dist: d42<3.0,>=2.0
Requires-Dist: jj<3.0,>=2.3.1
Requires-Dist: niltype<2.0,>=0.3
Requires-Dist: th<1.0,>=0.3
